jwk_theme/__init__.py
jwk_theme/static/css/base.css
jwk_theme/static/css/responsive.css
jwk_theme/static/css/style.css
jwk_theme/static/css/code_blocks/darkly.css
jwk_theme/static/css/code_blocks/github-light.css
jwk_theme/static/css/code_blocks/github.css
jwk_theme/static/css/code_blocks/monokai.css
jwk_theme/static/css/code_blocks/tomorrow.css
jwk_theme/static/css/code_blocks/tomorrow_night.css
jwk_theme/static/css/colors/beige.css
jwk_theme/static/css/colors/blue.css
jwk_theme/static/css/colors/brown.css
jwk_theme/static/css/colors/celadon.css
jwk_theme/static/css/colors/cherry.css
jwk_theme/static/css/colors/cyan.css
jwk_theme/static/css/colors/gray.css
jwk_theme/static/css/colors/green.css
jwk_theme/static/css/colors/navy.css
jwk_theme/static/css/colors/olive.css
jwk_theme/static/css/colors/orange.css
jwk_theme/static/css/colors/peach.css
jwk_theme/static/css/colors/pink.css
jwk_theme/static/css/colors/purple.css
jwk_theme/static/css/colors/red.css
jwk_theme/static/css/colors/yellow.css
jwk_theme/static/fonts/FontAwesome.otf
jwk_theme/static/fonts/fontawesome-webfont.eot
jwk_theme/static/fonts/fontawesome-webfont.svg
jwk_theme/static/fonts/fontawesome-webfont.ttf
jwk_theme/static/fonts/fontawesome-webfont.woff
jwk_theme/static/fonts/fontello.eot
jwk_theme/static/fonts/fontello.svg
jwk_theme/static/fonts/fontello.ttf
jwk_theme/static/fonts/fontello.woff
jwk_theme/static/images/blog-divider.png
jwk_theme/static/images/bg/bedge_grunge.png
jwk_theme/static/images/bg/brushed_alu.png
jwk_theme/static/images/bg/crisp_paper_ruffles.png
jwk_theme/static/images/bg/crissXcross.png
jwk_theme/static/images/bg/diamond_upholstery.png
jwk_theme/static/images/bg/egg_shell.png
jwk_theme/static/images/bg/light_toast.png
jwk_theme/static/images/bg/linedpaper.png
jwk_theme/static/images/bg/navy_blue.png
jwk_theme/static/images/bg/noise.png
jwk_theme/static/images/bg/noise_pattern_with_crosslines.png
jwk_theme/static/images/bg/purty_wood.png
jwk_theme-0.3.0.dist-info/METADATA
jwk_theme-0.3.0.dist-info/WHEEL
jwk_theme-0.3.0.dist-info/top_level.txt
jwk_theme-0.3.0.dist-info/RECORD
