Metadata-Version: 2.1
Name: jwk-theme
Version: 0.3.0
Summary: Pelican theme
Home-page: http://github.com/JWKennington/jwk-theme
Author: James W. Kennington
Author-email: jameswkennington@gmail.com
License: MIT
Platform: UNKNOWN
